pireal/__init__.py
pireal/dirs.py
pireal/keymap.py
pireal/main.py
pireal/resources.py
pireal/settings.py
pireal/translations.py
pireal/utils.py
pireal/core/__init__.py
pireal/core/cliparser.py
pireal/core/file_manager.py
pireal/core/logger.py
pireal/core/ordered_set.py
pireal/core/pfile.py
pireal/core/relation.py
pireal/core/rtypes.py
pireal/gui/__init__.py
pireal/gui/central_widget.py
pireal/gui/database_container.py
pireal/gui/lateral_widget.py
pireal/gui/main_window.py
pireal/gui/menu_actions.py
pireal/gui/model_view_delegate.py
pireal/gui/start_page.py
pireal/gui/table_widget.py
pireal/gui/theme.py
pireal/gui/updater.py
pireal/gui/dialogs/__init__.py
pireal/gui/dialogs/about_dialog.py
pireal/gui/dialogs/edit_relation_dialog.py
pireal/gui/dialogs/new_database_dialog.py
pireal/gui/dialogs/new_relation_dialog.py
pireal/gui/dialogs/preferences.py
pireal/gui/query_container/__init__.py
pireal/gui/query_container/editor.py
pireal/gui/query_container/highlighter.py
pireal/gui/query_container/query_container.py
pireal/gui/query_container/sidebar.py
pireal/gui/query_container/tab_widget.py
pireal/interpreter/__init__.py
pireal/interpreter/exceptions.py
pireal/interpreter/lexer.py
pireal/interpreter/parser.py
pireal/interpreter/rast.py
pireal/interpreter/scanner.py
pireal/interpreter/tokens.py
pireal/interpreter/utils.py
pireal/resources/images/pireal_icon.png
pireal/resources/samples/database.pdb
pireal/resources/samples/queries.pqf
pireal-3.1.0.data/scripts/pireal
pireal-3.1.0.dist-info/COPYING
pireal-3.1.0.dist-info/METADATA
pireal-3.1.0.dist-info/WHEEL
pireal-3.1.0.dist-info/top_level.txt
pireal-3.1.0.dist-info/RECORD
