Metadata-Version: 2.1
Name: pireal
Version: 3.1.0
Summary: Relational Algebra Interpreter
Home-page: https://centaurialpha.github.io/pireal
Author: Gabriel Acosta
Author-email: acostadariogabriel@gmail.com
License: GPLv3+
Project-URL: Bug Tracker, https://github.com/centaurialpha/pireal/issues
Platform: UNKNOWN
Classifier: Environment :: X11 Applications
Classifier: Operating System :: OS Independent
Classifier: Programming Language :: Python :: 3
Classifier: Topic :: Education
Classifier: Topic :: Utilities
License-File: COPYING
Requires-Dist: PyQt5 (>=5.15)
Provides-Extra: dev
Requires-Dist: ipython ; extra == 'dev'
Provides-Extra: test
Requires-Dist: flake8 ; extra == 'test'
Requires-Dist: pycodestyle ; extra == 'test'
Requires-Dist: pytest ; extra == 'test'
Requires-Dist: pytest-cov ; extra == 'test'
